{
  "impressions_history_chaining_seen": [
    {
      "string_map_data": {
        "Username": {
          "value": "stevegiralt"
        },
        "Time": {
          "timestamp": 1562165149
        }
      }
    },
    {
      "string_map_data": {
        "Username": {
          "value": "yellandross"
        },
        "Time": {
          "timestamp": 1548747840
        }
      }
    },
    {
      "string_map_data": {
        "Username": {
          "value": "whenharrymetswanny"
        },
        "Time": {
          "timestamp": 1547607807
        }
      }
    },
    {
      "string_map_data": {
        "Username": {
          "value": "98carrollchloe"
        },
        "Time": {
          "timestamp": 1547607698
        }
      }
    },
    {
      "string_map_data": {
        "Username": {
          "value": "markquinan2018"
        },
        "Time": {
          "timestamp": 1547001610
        }
      }
    },
    {
      "string_map_data": {
        "Username": {
          "value": "keysandbeatsmusic"
        },
        "Time": {
          "timestamp": 1542607930
        }
      }
    },
    {
      "string_map_data": {
        "Username": {
          "value": "margaret.jenkins.75286"
        },
        "Time": {
          "timestamp": 1538741198
        }
      }
    },
    {
      "string_map_data": {
        "Username": {
          "value": "kathybug_"
        },
        "Time": {
          "timestamp": 1536323694
        }
      }
    },
    {
      "string_map_data": {
        "Username": {
          "value": "runningdaball"
        },
        "Time": {
          "timestamp": 1531873152
        }
      }
    },
    {
      "string_map_data": {
        "Username": {
          "value": "bed_j.w._ford"
        },
        "Time": {
          "timestamp": 1529738419
        }
      }
    },
    {
      "string_map_data": {
        "Username": {
          "value": "sajad.zoleykani"
        },
        "Time": {
          "timestamp": 1519958792
        }
      }
    },
    {
      "string_map_data": {
        "Username": {
          "value": "whiteknight69lololol"
        },
        "Time": {
          "timestamp": 1515454500
        }
      }
    },
    {
      "string_map_data": {
        "Username": {
          "value": "jobantus74"
        },
        "Time": {
          "timestamp": 1513945314
        }
      }
    },
    {
      "string_map_data": {
        "Username": {
          "value": "prattprattpratt"
        },
        "Time": {
          "timestamp": 1512863974
        }
      }
    },
    {
      "string_map_data": {
        "Username": {
          "value": "erin_tequila"
        },
        "Time": {
          "timestamp": 1509242864
        }
      }
    },
    {
      "string_map_data": {
        "Username": {
          "value": "saumshemdoe"
        },
        "Time": {
          "timestamp": 1508201261
        }
      }
    },
    {
      "string_map_data": {
        "Username": {
          "value": "wissembaneni"
        },
        "Time": {
          "timestamp": 1506723047
        }
      }
    },
    {
      "string_map_data": {
        "Username": {
          "value": "coolmoonhaha"
        },
        "Time": {
          "timestamp": 1506723047
        }
      }
    },
    {
      "string_map_data": {
        "Username": {
          "value": "aichzine"
        },
        "Time": {
          "timestamp": 1506713312
        }
      }
    },
    {
      "string_map_data": {
        "Username": {
          "value": "hollajackgirl_"
        },
        "Time": {
          "timestamp": 1506571599
        }
      }
    },
    {
      "string_map_data": {
        "Username": {
          "value": "nicolasdiaz6275"
        },
        "Time": {
          "timestamp": 1506568408
        }
      }
    },
    {
      "string_map_data": {
        "Username": {
          "value": "kozthom"
        },
        "Time": {
          "timestamp": 1506567542
        }
      }
    },
    {
      "string_map_data": {
        "Username": {
          "value": "morgan_fox13"
        },
        "Time": {
          "timestamp": 1504518367
        }
      }
    },
    {
      "string_map_data": {
        "Username": {
          "value": "emj_24_"
        },
        "Time": {
          "timestamp": 1504516806
        }
      }
    },
    {
      "string_map_data": {
        "Username": {
          "value": "liangsisi7410"
        },
        "Time": {
          "timestamp": 1504514956
        }
      }
    },
    {
      "string_map_data": {
        "Username": {
          "value": "ddddoggo"
        },
        "Time": {
          "timestamp": 1504236009
        }
      }
    },
    {
      "string_map_data": {
        "Username": {
          "value": "emmajohnson7266"
        },
        "Time": {
          "timestamp": 1504210176
        }
      }
    },
    {
      "string_map_data": {
        "Username": {
          "value": "draculaclothing"
        },
        "Time": {
          "timestamp": 1499837890
        }
      }
    },
    {
      "string_map_data": {
        "Username": {
          "value": "steampunktendencies"
        },
        "Time": {
          "timestamp": 1499680747
        }
      }
    },
    {
      "string_map_data": {
        "Username": {
          "value": "rafael_a.b_"
        },
        "Time": {
          "timestamp": 1495785921
        }
      }
    },
    {
      "string_map_data": {
        "Username": {
          "value": "chillwind_yo"
        },
        "Time": {
          "timestamp": 1495785872
        }
      }
    },
    {
      "string_map_data": {
        "Username": {
          "value": "xettrisusmi"
        },
        "Time": {
          "timestamp": 1495785713
        }
      }
    },
    {
      "string_map_data": {
        "Username": {
          "value": "somjitchaiyawong"
        },
        "Time": {
          "timestamp": 1495021646
        }
      }
    },
    {
      "string_map_data": {
        "Username": {
          "value": "sherbetbirdie_photography"
        },
        "Time": {
          "timestamp": 1494842967
        }
      }
    },
    {
      "string_map_data": {
        "Username": {
          "value": "michelleobama"
        },
        "Time": {
          "timestamp": 1494759744
        }
      }
    },
    {
      "string_map_data": {
        "Username": {
          "value": "punkprincessstudios"
        },
        "Time": {
          "timestamp": 1494759744
        }
      }
    },
    {
      "string_map_data": {
        "Username": {
          "value": "naumovsveta"
        },
        "Time": {
          "timestamp": 1494755408
        }
      }
    },
    {
      "string_map_data": {
        "Username": {
          "value": "melissakatherinephotography"
        },
        "Time": {
          "timestamp": 1494755399
        }
      }
    },
    {
      "string_map_data": {
        "Username": {
          "value": "xapissjahatxcrkout"
        },
        "Time": {
          "timestamp": 1493073127
        }
      }
    },
    {
      "string_map_data": {
        "Username": {
          "value": "fero.feromeni"
        },
        "Time": {
          "timestamp": 1493073126
        }
      }
    },
    {
      "string_map_data": {
        "Username": {
          "value": "alyssakeely11"
        },
        "Time": {
          "timestamp": 1491008822
        }
      }
    },
    {
      "string_map_data": {
        "Username": {
          "value": "rebeccama05"
        },
        "Time": {
          "timestamp": 1491006815
        }
      }
    },
    {
      "string_map_data": {
        "Username": {
          "value": "perryannecoker"
        },
        "Time": {
          "timestamp": 1491001809
        }
      }
    }
  ]
}