{
  "story_activities_emoji_sliders": [
    {
      "title": "doll_cat_pvssy",
      "string_list_data": [
        {
          "value": "0",
          "timestamp": 1609501807
        }
      ]
    },
    {
      "title": "mjosexton",
      "string_list_data": [
        {
          "value": "100",
          "timestamp": 1528721919
        }
      ]
    },
    {
      "title": "thegrounds",
      "string_list_data": [
        {
          "value": "49.0125",
          "timestamp": 1526556329
        }
      ]
    }
  ]
}